target_clickhouse/__init__.py
target_clickhouse/connectors.py
target_clickhouse/engine_class.py
target_clickhouse/sinks.py
target_clickhouse/target.py
shaped_target_clickhouse-0.2.5.dist-info/LICENSE
shaped_target_clickhouse-0.2.5.dist-info/METADATA
shaped_target_clickhouse-0.2.5.dist-info/WHEEL
shaped_target_clickhouse-0.2.5.dist-info/entry_points.txt
shaped_target_clickhouse-0.2.5.dist-info/RECORD
