Metadata-Version: 2.1
Name: shaped-target-clickhouse
Version: 0.2.5
Summary: `target-clickhouse` is a Singer target for clickhouse, built with the Meltano Singer SDK.
License: Apache-2.0
Keywords: ELT,clickhouse
Author: Ben Theunissen
Requires-Python: >=3.8.0,<3.12
Classifier: License :: OSI Approved :: Apache Software License
Classifier: Programming Language :: Python :: 3
Classifier: Programming Language :: Python :: 3.8
Classifier: Programming Language :: Python :: 3.9
Classifier: Programming Language :: Python :: 3.10
Classifier: Programming Language :: Python :: 3.11
Provides-Extra: s3
Requires-Dist: clickhouse-sqlalchemy (>=0.3.0,<0.4.0)
Requires-Dist: fs-s3fs (>=1.1.1,<2.0.0) ; extra == "s3"
Requires-Dist: simplejson (>=3.19.2,<4.0.0)
Requires-Dist: singer-sdk (>=0.28,<0.37)
